Auto_connect_mongo/__init__.py
Auto_connect_mongo/mongo_crud.py
auto_connect_mongo-0.0.8.dist-info/LICENSE
auto_connect_mongo-0.0.8.dist-info/METADATA
auto_connect_mongo-0.0.8.dist-info/WHEEL
auto_connect_mongo-0.0.8.dist-info/top_level.txt
auto_connect_mongo-0.0.8.dist-info/RECORD
